LICENSE.txt
README.md
setup.py
linear_model/linear_model.py
trying_packages_linear_model.egg-info/PKG-INFO
trying_packages_linear_model.egg-info/SOURCES.txt
trying_packages_linear_model.egg-info/dependency_links.txt
trying_packages_linear_model.egg-info/requires.txt
trying_packages_linear_model.egg-info/top_level.txt