Metadata-Version: 2.1
Name: trying-packages-linear-model
Version: 1.0.0
Summary: An awesome package that does something
Home-page: http://pypi.python.org/pypi/linear_model/
Author: me
Author-email: assia@gmail.com
License: LICENSE.txt
Platform: UNKNOWN
License-File: LICENSE.txt
